Metadata-Version: 2.1
Name: cosh
Version: 0.3.8
Summary: Container Shell
Home-page: https://github.com/i11/cosh
Author: Ilja Bobkevic
Author-email: ilja@bobkevic.com
License:                     GNU GENERAL PUBLIC LICENSE
